<?xml version="1.0" encoding="utf-8"?>
<stb_file>
	<file_info>
		<strs>177</strs>
		<file_name>/resources/en-us/str/cnv/exp/seasons/01/ep_02/scene_01_valkorion.stb</file_name>
	</file_info>
	<file_content>
		<text bitflag="1345" id1="1156606" id2="17" version="1065353216">I have always loved the stars.</text>
		<text bitflag="1345" id1="1156607" id2="17" version="1065353216">Your death was too good to be true. You can't fool me.</text>
		<text bitflag="1360" id1="1156607" id2="17" version="1065353216">I knew you weren't dead.</text>
		<text bitflag="1345" id1="1156608" id2="17" version="1065353216">Deception was not my desire. You deserve truth.</text>
		<text bitflag="1360" id1="1156610" id2="17" version="1065353216">Get out of my mind.</text>
		<text bitflag="1345" id1="1156612" id2="17" version="1065353216">You won't control me again. I'm stronger than I was back then.</text>
		<text bitflag="1345" id1="1156613" id2="17" version="1065353216">Yes, I feel it.</text>
		<text bitflag="1345" id1="1156615" id2="17" version="1065353216">You can invade my mind, but I'll never become one of your Children.</text>
		<text bitflag="1345" id1="1156616" id2="17" version="1065353216">I no longer require a slave.</text>
		<text bitflag="1345" id1="1156618" id2="17" version="1065353216">I don't know how you're in my head, but I've got unlimited ammo here.</text>
		<text bitflag="1345" id1="1156619" id2="17" version="1065353216">You have nothing to fear.</text>
		<text bitflag="1345" id1="1156621" id2="17" version="1065353216">My brain isn't big enough for the both of us.</text>
		<text bitflag="1345" id1="1156622" id2="17" version="1065353216">Then we must expand it.</text>
		<text bitflag="1345" id1="1156624" id2="17" version="1065353216">You can enter my mind, but I won't bend to your will. I am no longer your Wrath.</text>
		<text bitflag="1345" id1="1156625" id2="17" version="1065353216">You have always been more than a title.</text>
		<text bitflag="1345" id1="1156627" id2="17" version="1065353216">I always hoped I'd add your spirit to my collection.</text>
		<text bitflag="1345" id1="1156628" id2="17" version="1065353216">I could say the same. This meeting is long overdue.</text>
		<text bitflag="1345" id1="1156630" id2="17" version="1065353216">You made a mistake getting inside my head. Just wait'll you see my dreams.</text>
		<text bitflag="1345" id1="1156631" id2="17" version="1065353216">I look forward to them.</text>
		<text bitflag="1345" id1="1156633" id2="17" version="1065353216">Just what I needed--one more mental stowaway to ignore.</text>
		<text bitflag="1345" id1="1156634" id2="17" version="1065353216">You do have a crowded mind.</text>
		<text bitflag="1345" id1="1156636" id2="17" version="1065353216">The next time we fight I'll drop you into one of them. See if that finishes you off.</text>
		<text bitflag="1360" id1="1156636" id2="17" version="1065353216">Maybe a star can kill you.</text>
		<text bitflag="1345" id1="1156637" id2="17" version="1065353216">You would not be the first to try, but you could be the first to succeed.</text>
		<text bitflag="1345" id1="1156639" id2="17" version="1065353216">You are much more than merely a Jedi.</text>
		<text bitflag="1345" id1="1156641" id2="17" version="1065353216">To call you Sith is to ignore your true self.</text>
		<text bitflag="1345" id1="1156643" id2="17" version="1065353216">You cannot wield the Force, yet you triumph over powers far greater.</text>
		<text bitflag="1345" id1="1156645" id2="17" version="1065353216">You have earned my respect. I followed you here so we might speak undisturbed.</text>
		<text bitflag="1360" id1="1156646" id2="17" version="1065353216">You've changed.</text>
		<text bitflag="1345" id1="1156648" id2="17" version="1065353216">You're not the same Emperor I fought on Dromund Kaas or Ziost.</text>
		<text bitflag="1345" id1="1156649" id2="17" version="1065353216">Everything changes. You most of all.</text>
		<text bitflag="1345" id1="1156650" id2="17" version="1065353216">Do you finally see the futility of the dark side?</text>
		<text bitflag="1345" id1="1156651" id2="17" version="1065353216">I have evolved beyond light and dark. So will you.</text>
		<text bitflag="1345" id1="1156652" id2="17" version="1065353216">The true Emperor follows no one. You are not him.</text>
		<text bitflag="1345" id1="1156653" id2="17" version="1065353216">You focus too much on the past. All things evolve.</text>
		<text bitflag="1345" id1="1156654" id2="17" version="1065353216">You've grown quite humble. Do you finally accept my superiority?</text>
		<text bitflag="1345" id1="1156655" id2="17" version="1065353216">I accept the need for change--and so must you.</text>
		<text bitflag="1345" id1="1156656" id2="17" version="1065353216">You're not the same lunatic I fought back on Ziost.</text>
		<text bitflag="1345" id1="1156657" id2="17" version="1065353216">I am, and am not. Change overtakes us all in the end.</text>
		<text bitflag="1345" id1="1156658" id2="17" version="1065353216">I don't have time for you.</text>
		<text bitflag="1360" id1="1156658" id2="17" version="1065353216">Too bad--I'm not listening.</text>
		<text bitflag="1345" id1="1156659" id2="17" version="1065353216">On the contrary, time is all you have. Use it to evolve.</text>
		<text bitflag="1345" id1="1156660" id2="17" version="1065353216">You're not planning to propose, are you?</text>
		<text bitflag="1360" id1="1156660" id2="17" version="1065353216">Are you flirting with me?</text>
		<text bitflag="1345" id1="1156661" id2="17" version="1065353216">Do not play the fool. The galaxy changes and we must change with it.</text>
		<text bitflag="1345" id1="1156665" id2="17" version="1065353216">Your true believers. You gave their lives purpose and meaning.</text>
		<text bitflag="1345" id1="1156667" id2="17" version="1065353216">A doubting Jedi....</text>
		<text bitflag="1345" id1="1156669" id2="17" version="1065353216">The broken healer...</text>
		<text bitflag="1345" id1="1156671" id2="17" version="1065353216">A mechanical servant....</text>
		<text bitflag="1345" id1="1156673" id2="17" version="1065353216">A lost soldier....</text>
		<text bitflag="1345" id1="1156675" id2="17" version="1065353216">And the unrepentant traitor.</text>
		<text bitflag="1345" id1="1156677" id2="17" version="1065353216">They were useful when you did not know yourself. But now, you are complete.</text>
		<text bitflag="1345" id1="1156678" id2="17" version="1065353216">I thought you knew all my secrets. You didn't know I fell in love?</text>
		<text bitflag="1360" id1="1156678" id2="17" version="1065353216">Not without my true love.</text>
		<text bitflag="1345" id1="1156679" id2="17" version="1065353216">Even a powerful Jedi is better when they have allies they can count on.</text>
		<text bitflag="1360" id1="1156679" id2="17" version="1065353216">Nothing beats a good team-up.</text>
		<text bitflag="1345" id1="1156680" id2="17" version="1065353216">Yours already forget you.</text>
		<text bitflag="1345" id1="1156681" id2="17" version="1065353216">You want to isolate me. It won't work.</text>
		<text bitflag="1345" id1="1156684" id2="17" version="1065353216">The Barsen'thor's loyal crew. Strange company for a Warden of the Order.</text>
		<text bitflag="1345" id1="1156686" id2="17" version="1065353216">There's the bestial seeker....</text>
		<text bitflag="1345" id1="1156688" id2="17" version="1065353216">A dissolute gambler....</text>
		<text bitflag="1345" id1="1156690" id2="17" version="1065353216">The spiteful revolutionary....</text>
		<text bitflag="1345" id1="1156692" id2="17" version="1065353216">A foolish idealist....</text>
		<text bitflag="1345" id1="1156694" id2="17" version="1065353216">And your naive acolyte.</text>
		<text bitflag="1345" id1="1156696" id2="17" version="1065353216">Why do you keep them? Is it obligation, pity, or simple inertia?</text>
		<text bitflag="1345" id1="1156697" id2="17" version="1065353216">Some bonds run deeper than any of those things. I found love with one of them.</text>
		<text bitflag="1360" id1="1156697" id2="17" version="1065353216">For one of them, it's love.</text>
		<text bitflag="1345" id1="1156698" id2="17" version="1065353216">You violated your Jedi Code. Impressive.</text>
		<text bitflag="1345" id1="1156700" id2="17" version="1065353216">I follow the will of the Force where it leads. It guided me to join them.</text>
		<text bitflag="1360" id1="1156700" id2="17" version="1065353216">The Force brought us together.</text>
		<text bitflag="1345" id1="1156701" id2="17" version="1065353216">And if the Force pulls you apart again, what then?</text>
		<text bitflag="1345" id1="1156702" id2="17" version="1065353216">I will accept that if I must.</text>
		<text bitflag="1345" id1="1156705" id2="17" version="1065353216">Your Havoc Squad. Its members followed you beyond all reason.</text>
		<text bitflag="1345" id1="1156707" id2="17" version="1065353216">The bitter survivor....</text>
		<text bitflag="1345" id1="1156709" id2="17" version="1065353216">A self-righteous defector...</text>
		<text bitflag="1345" id1="1156711" id2="17" version="1065353216">A mindless patriot....</text>
		<text bitflag="1345" id1="1156713" id2="17" version="1065353216">The scheming manipulator....</text>
		<text bitflag="1345" id1="1156715" id2="17" version="1065353216">And a perpetual outsider.</text>
		<text bitflag="1345" id1="1156717" id2="17" version="1065353216">What becomes of soldiers without their leader? Warriors who lose their cause?</text>
		<text bitflag="1345" id1="1156718" id2="17" version="1065353216">Love keeps me fighting when nothing else will.</text>
		<text bitflag="1360" id1="1156718" id2="17" version="1065353216">One of them loves me.</text>
		<text bitflag="1345" id1="1156719" id2="17" version="1065353216">Havoc Squad's mission hasn't changed. They'll keep fighting.</text>
		<text bitflag="1360" id1="1156719" id2="17" version="1065353216">They still have a cause.</text>
		<text bitflag="1345" id1="1156720" id2="17" version="1065353216">Like machines executing a program. You are better than that.</text>
		<text bitflag="1345" id1="1156721" id2="17" version="1065353216">A commander's nothing without troops. We rely on each other.</text>
		<text bitflag="1345" id1="1156724" id2="17" version="1065353216">Your misfit crew. They aspire to your example but are merely shadows.</text>
		<text bitflag="1345" id1="1156726" id2="17" version="1065353216">The sentimental gunman....</text>
		<text bitflag="1345" id1="1156728" id2="17" version="1065353216">An apathetic monarch...</text>
		<text bitflag="1345" id1="1156730" id2="17" version="1065353216">Your dutiful beast....</text>
		<text bitflag="1345" id1="1156732" id2="17" version="1065353216">The artless fraud....</text>
		<text bitflag="1345" id1="1156734" id2="17" version="1065353216">And a forsaken avenger.</text>
		<text bitflag="1345" id1="1156736" id2="17" version="1065353216">You have no use for them.</text>
		<text bitflag="1345" id1="1156737" id2="17" version="1065353216">I share a bunk with one. That's been pretty useful.</text>
		<text bitflag="1360" id1="1156737" id2="17" version="1065353216">Being in love counts, right?</text>
		<text bitflag="1345" id1="1156738" id2="17" version="1065353216">I trust them to watch my back. Besides, they make me look good.</text>
		<text bitflag="1360" id1="1156738" id2="17" version="1065353216">They're loyal. That's enough.</text>
		<text bitflag="1345" id1="1156739" id2="17" version="1065353216">Without you they are nothing.</text>
		<text bitflag="1345" id1="1156740" id2="17" version="1065353216">Which is why I'm sure they're coming up with a plan to spring me.</text>
		<text bitflag="1345" id1="1156743" id2="17" version="1065353216">Your servants. They cling to you like parasites on a predator.</text>
		<text bitflag="1345" id1="1156745" id2="17" version="1065353216">Your thieving slave....</text>
		<text bitflag="1345" id1="1156747" id2="17" version="1065353216">The smiling betrayer....</text>
		<text bitflag="1345" id1="1156749" id2="17" version="1065353216">A deluded Jedi....</text>
		<text bitflag="1345" id1="1156751" id2="17" version="1065353216">The homicidal savage....</text>
		<text bitflag="1345" id1="1156753" id2="17" version="1065353216">And a reckless malcontent.</text>
		<text bitflag="1345" id1="1156755" id2="17" version="1065353216">You suffered their existence for years. Even those who earned death.</text>
		<text bitflag="1345" id1="1156756" id2="17" version="1065353216">One feeds my passion more than all the others combined.</text>
		<text bitflag="1360" id1="1156756" id2="17" version="1065353216">One earned my love.</text>
		<text bitflag="1345" id1="1156757" id2="17" version="1065353216">Most are loyal. I keep those who aren't as a reminder to never lower my guard.</text>
		<text bitflag="1360" id1="1156757" id2="17" version="1065353216">Even traitors have their uses.</text>
		<text bitflag="1345" id1="1156758" id2="17" version="1065353216">I once thought as you. It served me poorly.</text>
		<text bitflag="1345" id1="1156759" id2="17" version="1065353216">They will not fail me. I will be freed from this prison.</text>
		<text bitflag="1345" id1="1156762" id2="17" version="1065353216">Your acolytes. Rungs on the ladder of your ascent.</text>
		<text bitflag="1345" id1="1156764" id2="17" version="1065353216">The ageless fiend....</text>
		<text bitflag="1345" id1="1156766" id2="17" version="1065353216">An embittered pirate....</text>
		<text bitflag="1345" id1="1156768" id2="17" version="1065353216">Your worshipful academic....</text>
		<text bitflag="1345" id1="1156770" id2="17" version="1065353216">An impure Jedi....</text>
		<text bitflag="1345" id1="1156772" id2="17" version="1065353216">And a bloodthirsty zealot.</text>
		<text bitflag="1345" id1="1156774" id2="17" version="1065353216">They outlived their purpose long ago, yet you permit them to live.</text>
		<text bitflag="1345" id1="1156775" id2="17" version="1065353216">I'm not yet in the habit of murdering those I love. Call me sentimental.</text>
		<text bitflag="1360" id1="1156775" id2="17" version="1065353216">One is my lover.</text>
		<text bitflag="1345" id1="1156776" id2="17" version="1065353216">Clever Sith keep their allies close. You never know when you'll need a sacrifice.</text>
		<text bitflag="1360" id1="1156776" id2="17" version="1065353216">They may yet be useful.</text>
		<text bitflag="1345" id1="1156777" id2="17" version="1065353216">You think you need them. You do not.</text>
		<text bitflag="1345" id1="1156778" id2="17" version="1065353216">I'll decide that myself.</text>
		<text bitflag="1345" id1="1156781" id2="17" version="1065353216">Your mercenary crew. They follow you out of self-interest.</text>
		<text bitflag="1345" id1="1156783" id2="17" version="1065353216">The glory-seeking orphan....</text>
		<text bitflag="1345" id1="1156785" id2="17" version="1065353216">A cowardly scoundrel....</text>
		<text bitflag="1345" id1="1156787" id2="17" version="1065353216">The Mandalorian pretender....</text>
		<text bitflag="1345" id1="1156789" id2="17" version="1065353216">A naive wanderer....</text>
		<text bitflag="1345" id1="1156791" id2="17" version="1065353216">And a brutish psychopath.</text>
		<text bitflag="1345" id1="1156793" id2="17" version="1065353216">You no longer need that outlaw band. You never did.</text>
		<text bitflag="1345" id1="1156794" id2="17" version="1065353216">Maybe not all of them, but I've got someone special.</text>
		<text bitflag="1360" id1="1156794" id2="17" version="1065353216">There's one I love.</text>
		<text bitflag="1345" id1="1156795" id2="17" version="1065353216">I pay them to watch my back.</text>
		<text bitflag="1360" id1="1156795" id2="17" version="1065353216">They have their uses.</text>
		<text bitflag="1345" id1="1156796" id2="17" version="1065353216">Not anymore.</text>
		<text bitflag="1345" id1="1156797" id2="17" version="1065353216">They'll find me if they know what's good for them.</text>
		<text bitflag="1345" id1="1156800" id2="17" version="1065353216">Your conspirators. It is difficult to imagine a less trustworthy crew.</text>
		<text bitflag="1345" id1="1156802" id2="17" version="1065353216">A charming sociopath....</text>
		<text bitflag="1345" id1="1156804" id2="17" version="1065353216">An alienated diplomat....</text>
		<text bitflag="1345" id1="1156806" id2="17" version="1065353216">The unassuming monster....</text>
		<text bitflag="1345" id1="1156808" id2="17" version="1065353216">A wanted fugitive....</text>
		<text bitflag="1345" id1="1156810" id2="17" version="1065353216">And an amoral machine.</text>
		<text bitflag="1345" id1="1156812" id2="17" version="1065353216">Tell me, do they hope to rescue you... or confirm your demise?</text>
		<text bitflag="1345" id1="1156813" id2="17" version="1065353216">I know one who wants me back alive. We're in love.</text>
		<text bitflag="1360" id1="1156813" id2="17" version="1065353216">At least one of them loves me.</text>
		<text bitflag="1345" id1="1156814" id2="17" version="1065353216">Love withers when it is neglected. Left alone too long, love will seek another.</text>
		<text bitflag="1345" id1="1156815" id2="17" version="1065353216">We'll be together again.</text>
		<text bitflag="1345" id1="1156816" id2="17" version="1065353216">It's a bit of both. That's why we work together so well.</text>
		<text bitflag="1360" id1="1156816" id2="17" version="1065353216">Either way, they're useful.</text>
		<text bitflag="1345" id1="1156817" id2="17" version="1065353216">You see them clearly.</text>
		<text bitflag="1345" id1="1156818" id2="17" version="1065353216">Are you insulting my colleagues for a reason?</text>
		<text bitflag="1345" id1="1156819" id2="17" version="1065353216">Over here!</text>
		<text bitflag="1360" id1="1156819" id2="17" version="1065353216">[Call out to your allies.]</text>
		<text bitflag="1345" id1="1156820" id2="17" version="1065353216">What will that accomplish?</text>
		<text bitflag="1345" id1="1156821" id2="17" version="1065353216">I can stop talking to you.</text>
		<text bitflag="1345" id1="1156822" id2="17" version="1065353216">Not all of us belong together. I'm not sure why they stay.</text>
		<text bitflag="1360" id1="1156822" id2="17" version="1065353216">I'd replace some if I could.</text>
		<text bitflag="1345" id1="1156823" id2="17" version="1065353216">You admit the truth.</text>
		<text bitflag="1345" id1="1156825" id2="17" version="1065353216">Each day they drift further out of reach. Without a center to hold... without us... the galaxy and all within it spiral into chaos.</text>
		<text bitflag="1345" id1="1156828" id2="17" version="1065353216">What's happening to me....</text>
		<text bitflag="1345" id1="1156829" id2="17" version="1065353216">The carbon freezing was imperfect. Your body is poisoned. Dying.</text>
		<text bitflag="1345" id1="1156831" id2="17" version="1065353216">Old foes have come to take your life.</text>
		<text bitflag="1345" id1="1156832" id2="17" version="1065353216">I'm not afraid. None of this is real.</text>
		<text bitflag="1360" id1="1156832" id2="17" version="1065353216">Nightmares can't hurt me.</text>
		<text bitflag="1345" id1="1156833" id2="17" version="1065353216">Illusions can kill.</text>
		<text bitflag="1345" id1="1156835" id2="17" version="1065353216">I beat them before. I'll do it again.</text>
		<text bitflag="1360" id1="1156835" id2="17" version="1065353216">They'll fail.</text>
		<text bitflag="1345" id1="1156836" id2="17" version="1065353216">If you want to live, you must fight.</text>
		<text bitflag="1345" id1="1156837" id2="17" version="1065353216">I'm tired of talking. You want a fight? I'm ready!</text>
		<text bitflag="1360" id1="1156837" id2="17" version="1065353216">Come on, then!</text>
		<text bitflag="1345" id1="1156838" id2="17" version="1065353216">Yes. Good.</text>
		<text bitflag="1345" id1="1157033" id2="17" version="1065353216">A debased apprentice....</text>
		<text bitflag="1345" id1="1157034" id2="17" version="1065353216">Passion fades with distance.</text>
		<text bitflag="1345" id1="1157616" id2="17" version="1065353216">You can stargaze later. We had an agreement.</text>
		<text bitflag="1360" id1="1157616" id2="17" version="1065353216">What about our deal?</text>
		<text bitflag="1345" id1="1157617" id2="17" version="1065353216">Patience. We can still achieve what I promised.</text>
	</file_content>
</stb_file>
