<?xml version="1.0" encoding="utf-8"?>
<stb_file>
	<file_info>
		<strs>76</strs>
		<file_name>/resources/en-us/str/cnv/location/nar_shaddaa/class/spy/jt_05.stb</file_name>
	</file_info>
	<file_content>
		<text bitflag="321" id1="652581" id2="17" version="1065353216">[This appears to be an advanced-model serving droid. It shouldn't be difficult to add the poison into its drink dispenser.]</text>
		<text bitflag="336" id1="652582" id2="17" version="1065353216">[Poison the droid's drinks.]</text>
		<text bitflag="1345" id1="652587" id2="17" version="1065353216">Sorry--Master Tlan must have called the droid. I hope that's not a problem.</text>
		<text bitflag="1345" id1="652588" id2="17" version="1065353216">I was just finishing up.</text>
		<text bitflag="1360" id1="652588" id2="17" version="1065353216">No problem.</text>
		<text bitflag="1345" id1="652589" id2="17" version="1065353216">Great. Hope it worked out.</text>
		<text bitflag="1345" id1="652590" id2="17" version="1065353216">No rush. I'll take another look when it gets back.</text>
		<text bitflag="1360" id1="652590" id2="17" version="1065353216">I can wait.</text>
		<text bitflag="1345" id1="652591" id2="17" version="1065353216">That's fine with me.</text>
		<text bitflag="1345" id1="652592" id2="17" version="1065353216">Whatever you were doing with that droid, please leave it alone. Master Tlan's called it.</text>
		<text bitflag="1345" id1="652593" id2="17" version="1065353216">I was just curious. Didn't mean any harm.</text>
		<text bitflag="1360" id1="652593" id2="17" version="1065353216">Sorry.</text>
		<text bitflag="1345" id1="652594" id2="17" version="1065353216">That droid is for Master Tlan, and only Master Tlan. Don't bother it from now on.</text>
		<text bitflag="1345" id1="652595" id2="17" version="1065353216">I'm sure Master Tlan will enjoy his drink.</text>
		<text bitflag="1360" id1="652595" id2="17" version="1065353216">This should be interesting.</text>
		<text bitflag="1345" id1="652596" id2="17" version="1065353216">I'm sure he will.</text>
		<text bitflag="1345" id1="652597" id2="17" version="1065353216">I'm just staying occupied. Don't get touchy.</text>
		<text bitflag="1360" id1="652597" id2="17" version="1065353216">Enough already.</text>
		<text bitflag="1345" id1="652600" id2="17" version="1065353216">Netula! Netula! I can't breathe... I need my medical droids! I need them now!</text>
		<text bitflag="1345" id1="652602" id2="17" version="1065353216">Master, you have two medical droids already.</text>
		<text bitflag="1345" id1="652604" id2="17" version="1065353216">Idiot girl. I know when there's something wrong with me. I can't breathe. My tongue is swelling--there was something in my drink!</text>
		<text bitflag="1345" id1="652605" id2="17" version="1065353216">You're right, Tlan. You've just been poisoned.</text>
		<text bitflag="1360" id1="652605" id2="17" version="1065353216">I'm responsible.</text>
		<text bitflag="1345" id1="652606" id2="17" version="1065353216">Let me in--I'm a doctor.</text>
		<text bitflag="1360" id1="652606" id2="17" version="1065353216">I can help you.</text>
		<text bitflag="1345" id1="652607" id2="17" version="1065353216">Who the blazes are you?</text>
		<text bitflag="1345" id1="652608" id2="17" version="1065353216">Hello, Tlan. Sorry for the trouble--seemed the fastest way to get your attention.</text>
		<text bitflag="1360" id1="652608" id2="17" version="1065353216">I thought you'd notice that.</text>
		<text bitflag="1345" id1="652609" id2="17" version="1065353216">You did this? How did you get in here?</text>
		<text bitflag="1345" id1="652613" id2="17" version="1065353216">I'm sorry, master. This is the woman who wanted to meet with you.</text>
		<text bitflag="1345" id1="652614" id2="17" version="1065353216">I'm sorry, master. She came to look at the droids.</text>
		<text bitflag="1345" id1="652615" id2="17" version="1065353216">I'm sorry, master. She just came in and started playing with the serving droid. I couldn't stop her!</text>
		<text bitflag="1345" id1="652618" id2="17" version="1065353216">I'm sorry, master. This is the man who wanted to meet with you.</text>
		<text bitflag="1345" id1="652619" id2="17" version="1065353216">I'm sorry, master. He came to look at the droids.</text>
		<text bitflag="1345" id1="652620" id2="17" version="1065353216">I'm sorry, master. He just came in and started playing with the serving droid. I couldn't stop him!</text>
		<text bitflag="1345" id1="652622" id2="17" version="1065353216">You pathetic creature. I've told you that I have enemies--and this is proof! This woman is trying to kill me!</text>
		<text bitflag="1345" id1="652624" id2="17" version="1065353216">You pathetic creature. I've told you that I have enemies--and this is proof! This man is trying to kill me!</text>
		<text bitflag="1345" id1="652626" id2="17" version="1065353216">I'm so sorry. I had no idea...</text>
		<text bitflag="1345" id1="652628" id2="17" version="1065353216">You've got my undivided attention, blast you. What do you want?</text>
		<text bitflag="1345" id1="652629" id2="17" version="1065353216">I need to know about Synchet's link to terrorism.</text>
		<text bitflag="1360" id1="652629" id2="17" version="1065353216">It's about your business.</text>
		<text bitflag="1345" id1="652630" id2="17" version="1065353216">It's not--it wasn't like that.</text>
		<text bitflag="1345" id1="652632" id2="17" version="1065353216">Ever hear of a genetic modification program called &quot;Cyclone&quot;?</text>
		<text bitflag="1360" id1="652632" id2="17" version="1065353216">Tell me about this serum.</text>
		<text bitflag="1345" id1="652633" id2="17" version="1065353216">What? I'm not a geneticist.</text>
		<text bitflag="1345" id1="652635" id2="17" version="1065353216">You're supporting an uprising against the Empire.</text>
		<text bitflag="1360" id1="652635" id2="17" version="1065353216">Terrorist scum.</text>
		<text bitflag="1345" id1="652636" id2="17" version="1065353216">What? No! Do I look like someone who cares about politics?</text>
		<text bitflag="1345" id1="652638" id2="17" version="1065353216">I don't have any answers for you. Now help me, before I'm a corpse!</text>
		<text bitflag="1345" id1="652639" id2="17" version="1065353216">You know something. Talk to me, Tlan.</text>
		<text bitflag="1360" id1="652639" id2="17" version="1065353216">Liar.</text>
		<text bitflag="1345" id1="652640" id2="17" version="1065353216">Work with me. Try to remember back to Synchet's bankruptcy.</text>
		<text bitflag="1360" id1="652640" id2="17" version="1065353216">Please, I need your help.</text>
		<text bitflag="1345" id1="652641" id2="17" version="1065353216">Talk first, then the antidote.</text>
		<text bitflag="1360" id1="652641" id2="17" version="1065353216">I'm in no hurry.</text>
		<text bitflag="1345" id1="652642" id2="17" version="1065353216">You--blast you.</text>
		<text bitflag="1345" id1="652644" id2="17" version="1065353216">Back when I was with Synchet, the company was failing. The war bankrupted us. We had to sell everything.</text>
		<text bitflag="1345" id1="652646" id2="17" version="1065353216">One of our subsidiaries developed medical technologies--kolto tanks, rancor stims, Cyclone, that sort of thing. But the group that bought it wasn't interested in profit.</text>
		<text bitflag="1345" id1="652647" id2="17" version="1065353216">What were they interested in?</text>
		<text bitflag="1360" id1="652647" id2="17" version="1065353216">Go on.</text>
		<text bitflag="1345" id1="652648" id2="17" version="1065353216">Something seemed wrong, but you sold them the company anyway?</text>
		<text bitflag="1360" id1="652648" id2="17" version="1065353216">You dealt with this group?</text>
		<text bitflag="1345" id1="652649" id2="17" version="1065353216">Of course we did. Why not?</text>
		<text bitflag="1345" id1="652651" id2="17" version="1065353216">Maybe you'll earn the antidote after all.</text>
		<text bitflag="1360" id1="652651" id2="17" version="1065353216">You're making me happy.</text>
		<text bitflag="1345" id1="652652" id2="17" version="1065353216">They used fake names, paid for everything in cash.</text>
		<text bitflag="1345" id1="652654" id2="17" version="1065353216">They only cared about the technology, not the business. Yes, I knew it was strange, and no, I didn't--didn't...</text>
		<text bitflag="1345" id1="652656" id2="17" version="1065353216">Get in there and help him! Or do you just plan to let him die?</text>
		<text bitflag="1345" id1="652657" id2="17" version="1065353216">I'll bring him the antidote. Open the door.</text>
		<text bitflag="1360" id1="652657" id2="17" version="1065353216">Not yet.</text>
		<text bitflag="1345" id1="652658" id2="17" version="1065353216">I'll make sure your boss doesn't expire.</text>
		<text bitflag="1360" id1="652658" id2="17" version="1065353216">Don't worry.</text>
		<text bitflag="1345" id1="652659" id2="17" version="1065353216">He's not going to die until I'm finished.</text>
		<text bitflag="1360" id1="652659" id2="17" version="1065353216">There's more I can do to him.</text>
		<text bitflag="336" id1="652663" id2="17" version="1065353216">[Leave the droid alone.]</text>
		<text bitflag="3393" id1="652666" id2="17" version="1065353216">Speaker = not master. Access denied.</text>
	</file_content>
</stb_file>
