<?xml version="1.0" encoding="utf-8"?>
<stb_file>
	<file_info>
		<strs>1</strs>
		<file_name>/resources/en-us/str/cnv/exp/01/makeb/support/imperial/westwater/mission_terminal.stb</file_name>
	</file_info>
	<file_content>
		<text bitflag="321" id1="1112655" id2="17" version="1065353216">MISSION ASSISTANCE--BY ORDER OF IMPERIAL COMMAND--MESSAGE READS:

An Imperial probe droid has identified key operatives in the occupation of the Westwater Settlements by the InterStellar Regulators. Eliminating these operatives will increase the locals' chances of mounting a successful revolt against the Regulators, thereby furthering our goals.

For the Empire.

END MESSAGE</text>
	</file_content>
</stb_file>
