<?xml version="1.0" encoding="utf-8"?>
<stb_file>
	<file_info>
		<strs>74</strs>
		<file_name>/resources/en-us/str/cnv/location/taris_imp/class/spy/doctor_ianna_cel.stb</file_name>
	</file_info>
	<file_content>
		<text bitflag="1345" id1="618920" id2="17" version="1065353216">Cipher! I'm sorry to interrupt, but I believe I have a solution for both you and Doctor Cel.</text>
		<text bitflag="1360" id1="618921" id2="17" version="1065353216">I'm listening.</text>
		<text bitflag="1345" id1="618922" id2="17" version="1065353216">Let me speak to the scientist, please.</text>
		<text bitflag="1345" id1="618926" id2="17" version="1065353216">You want to explain where you heard that name?</text>
		<text bitflag="1360" id1="618926" id2="17" version="1065353216">How do you know about Cel?</text>
		<text bitflag="1345" id1="618927" id2="17" version="1065353216">Yes, well. I was hoping you wouldn't ask that.</text>
		<text bitflag="1345" id1="618931" id2="17" version="1065353216">We can discuss this later, doctor.</text>
		<text bitflag="1360" id1="618931" id2="17" version="1065353216">Now's a bad time. [Disconnect]</text>
		<text bitflag="1345" id1="618934" id2="17" version="1065353216">You disconnected me. I'm disappointed.</text>
		<text bitflag="1345" id1="618936" id2="17" version="1065353216">Who is this?</text>
		<text bitflag="1345" id1="618938" id2="17" version="1065353216">Doctor Eckard Lokin. I'm going to be your assistant, and be captured in your place.</text>
		<text bitflag="1345" id1="618940" id2="17" version="1065353216">Are you joking?</text>
		<text bitflag="1345" id1="618942" id2="17" version="1065353216">I wouldn't joke about this, doctor--I saw your lecture on xenometamorphic epidemiology, and a mind like yours should be kept safe.</text>
		<text bitflag="1345" id1="618944" id2="17" version="1065353216">Imagine: Ki Sazen takes me instead of her, and brings me to the Ultrawave Transmitter. I signal you, and you find everything you want in one place.</text>
		<text bitflag="1345" id1="618945" id2="17" version="1065353216">Doctor Eckard Lokin. I saw your lecture on xenometamorphic epidemiology.</text>
		<text bitflag="1345" id1="618947" id2="17" version="1065353216">I understand your misgivings. &quot;How did he track me here?&quot; &quot;How did he survive the ruins unscathed?&quot; Both reasonable questions.</text>
		<text bitflag="1345" id1="618949" id2="17" version="1065353216">But like you, I'm a resourceful person, and we do share a common goal. We're all friends of the Republic here--right, Doctor Cel?</text>
		<text bitflag="1345" id1="618950" id2="17" version="1065353216">You're starting to make me wonder. That's not good for your prospects.</text>
		<text bitflag="1360" id1="618950" id2="17" version="1065353216">I have my doubts.</text>
		<text bitflag="1345" id1="618951" id2="17" version="1065353216">We can discuss our &quot;common interests&quot; another time. Make your pitch.</text>
		<text bitflag="1360" id1="618951" id2="17" version="1065353216">We'll talk about this later.</text>
		<text bitflag="1345" id1="618952" id2="17" version="1065353216">Thank you. Doctor Cel, I'd like you to tell the Republic that I'm your assistant.</text>
		<text bitflag="1345" id1="618954" id2="17" version="1065353216">Same goal or not... a blaster to the head solves my problem.</text>
		<text bitflag="1360" id1="618954" id2="17" version="1065353216">Maybe I should just kill you.</text>
		<text bitflag="1345" id1="618955" id2="17" version="1065353216">Paranoia can be healthy, but it doesn't get you closer to the Jedi. Only Doctor Cel can do that--by revealing that I am her assistant.</text>
		<text bitflag="1345" id1="618957" id2="17" version="1065353216">You've got to be kidding.</text>
		<text bitflag="1345" id1="618959" id2="17" version="1065353216">I know rakghoul science well enough to convince Ki Sazen that I'm an adequate substitute for Cel. I'll be taken to the Ultrawave Transmitter.</text>
		<text bitflag="1345" id1="618961" id2="17" version="1065353216">Once captive, I signal you, and you find Ki Sazen and the transmitter. And rescue me, of course.</text>
		<text bitflag="1345" id1="618962" id2="17" version="1065353216">Would Ki Sazen believe this man is your assistant?</text>
		<text bitflag="1360" id1="618962" id2="17" version="1065353216">Your opinion, Doctor Cel?</text>
		<text bitflag="1345" id1="618963" id2="17" version="1065353216">What's the difference between a Hirano strain of the rakghoul virus and the Bozan variant?</text>
		<text bitflag="1345" id1="618965" id2="17" version="1065353216">Aside from the phenotypic switching controversy?</text>
		<text bitflag="1345" id1="618967" id2="17" version="1065353216">Mutation of the Clawdite-derived gene sequence.</text>
		<text bitflag="1345" id1="618969" id2="17" version="1065353216">She'll believe him.</text>
		<text bitflag="1345" id1="618971" id2="17" version="1065353216">It's not a bad plan. We might even survive it.</text>
		<text bitflag="1360" id1="618971" id2="17" version="1065353216">That might work.</text>
		<text bitflag="1345" id1="618972" id2="17" version="1065353216">If you deviate from the plan, you won't get out alive.</text>
		<text bitflag="1360" id1="618972" id2="17" version="1065353216">You'll obey my orders.</text>
		<text bitflag="1345" id1="618973" id2="17" version="1065353216">I'm a humble scientist. I'll follow you every step of the way.</text>
		<text bitflag="1345" id1="618975" id2="17" version="1065353216">Understood.</text>
		<text bitflag="1345" id1="618977" id2="17" version="1065353216">Doctor, please contact the authorities on an unsecured channel. Tell them your assistant is at these coordinates, and must be found.</text>
		<text bitflag="1345" id1="618979" id2="17" version="1065353216">Doctor, please contact the authorities on an unsecured channel. Tell them your assistant is at Dynamet General, and must be found.</text>
		<text bitflag="1345" id1="618981" id2="17" version="1065353216">It's your life on the line. Just be careful--both of you.</text>
		<text bitflag="1345" id1="618983" id2="17" version="1065353216">One final concern--once I'm captured, the Republic may attempt jam my signal to you.</text>
		<text bitflag="1345" id1="618985" id2="17" version="1065353216">I suggest you use this time to sabotage their jamming stations. By the time you're done, I'll surely be in enemy hands.</text>
		<text bitflag="1345" id1="618990" id2="17" version="1065353216">One last thing, while I wait to be captured. There is a chance the Republic will jam my signal to you.</text>
		<text bitflag="1345" id1="618992" id2="17" version="1065353216">Before you come for Ki Sazen, you'll have to sabotage their jamming stations. They're guarded by wilderness troopers--a good warm-up for fighting a Jedi Knight.</text>
		<text bitflag="1345" id1="618997" id2="17" version="1065353216">Doctor Ianna Cel? I'm with the SIS. Password: &quot;gemstone.&quot; You agreed to meet with us.</text>
		<text bitflag="1345" id1="619000" id2="17" version="1065353216">Don't move. Just... hell, I barely know how to fire one of these things.</text>
		<text bitflag="1345" id1="619004" id2="17" version="1065353216">You have no idea how glad I am to see you--I've been hiding from that Jedi for weeks.</text>
		<text bitflag="1345" id1="619005" id2="17" version="1065353216">What do you know about Ki Sazen, and why she's after you?</text>
		<text bitflag="1360" id1="619005" id2="17" version="1065353216">Tell me about the Jedi.</text>
		<text bitflag="1345" id1="619006" id2="17" version="1065353216">Have you been holed up in here this whole time?</text>
		<text bitflag="1360" id1="619006" id2="17" version="1065353216">How did you survive?</text>
		<text bitflag="1345" id1="619007" id2="17" version="1065353216">Mostly. I've been living off ration bars and some kind of edible hospital gel that even the rakghouls won't touch.</text>
		<text bitflag="1345" id1="619009" id2="17" version="1065353216">If you don't make this worth my while, I can still let her have you.</text>
		<text bitflag="1360" id1="619009" id2="17" version="1065353216">You'd better cooperate.</text>
		<text bitflag="1345" id1="619010" id2="17" version="1065353216">Let me show you something. I kept it with me as evidence.</text>
		<text bitflag="1345" id1="619012" id2="17" version="1065353216">Doctor Cel. You haven't returned my calls. That's disappointing.</text>
		<text bitflag="1345" id1="619014" id2="17" version="1065353216">The Jedi have plans for the rakghouls, but I can't move forward without your support.</text>
		<text bitflag="1345" id1="619016" id2="17" version="1065353216">Turn yourself over to the Nikto, or I'll make my case to you in person.</text>
		<text bitflag="1345" id1="619018" id2="17" version="1065353216">She's not a Jedi. She already killed Doctor Vernon and Professor Vraal when they couldn't fix some transmitter. I'm the last rakghoul expert on Taris.</text>
		<text bitflag="1345" id1="619019" id2="17" version="1065353216">She needs you to complete a device for controlling rakghouls.</text>
		<text bitflag="1360" id1="619019" id2="17" version="1065353216">The Ultrawave Transmitter.</text>
		<text bitflag="5441" id1="619020" id2="17" version="1065353216">Of course she does. She's completely crazy...</text>
		<text bitflag="1345" id1="619021" id2="17" version="1065353216">Can you tell me where she is?</text>
		<text bitflag="1360" id1="619021" id2="17" version="1065353216">I need to find her.</text>
		<text bitflag="5441" id1="619022" id2="17" version="1065353216">No, and if I stick my head out, she'll see me.</text>
		<text bitflag="1345" id1="619023" id2="17" version="1065353216">If you really are the last, then it's over. The Ultrawave Transmitter is a dead project.</text>
		<text bitflag="1360" id1="619023" id2="17" version="1065353216">She can't win without you.</text>
		<text bitflag="5441" id1="619024" id2="17" version="1065353216">Assuming she doesn't find another way. And if she's halfway there...</text>
		<text bitflag="1345" id1="619026" id2="17" version="1065353216">If that's yours, I can wait.</text>
		<text bitflag="1345" id1="619029" id2="17" version="1065353216">What is it?</text>
		<text bitflag="1345" id1="619030" id2="17" version="1065353216">Keep your voice down. It's not safe in here.</text>
	</file_content>
</stb_file>
